aws_recommendation_a5/__init__.py
aws_recommendation_a5/cloudwatch.py
aws_recommendation_a5/cost_estimations.py
aws_recommendation_a5/dynamodb.py
aws_recommendation_a5/ebs.py
aws_recommendation_a5/ec2.py
aws_recommendation_a5/elb.py
aws_recommendation_a5/kms.py
aws_recommendation_a5/rds.py
aws_recommendation_a5/recommendation.py
aws_recommendation_a5/redshift.py
aws_recommendation_a5/s3.py
aws_recommendation_a5/truted_advisor.py
aws_recommendation_a5/utils.py
aws_recommendation_a5-0.0.17.dist-info/LICENCE
aws_recommendation_a5-0.0.17.dist-info/METADATA
aws_recommendation_a5-0.0.17.dist-info/WHEEL
aws_recommendation_a5-0.0.17.dist-info/top_level.txt
aws_recommendation_a5-0.0.17.dist-info/RECORD
