Metadata-Version: 2.1
Name: aws_recommendation_a5
Version: 0.0.17
Summary: Provides AWS recommendations
Author-email: "dheeraj.banodha" <dheerajmbanodha@gmail.com>
Classifier: Programming Language :: Python :: 3
Classifier: Operating System :: OS Independent
Requires-Python: >=3.7
License-File: LICENCE
